xblock/__init__.py
xblock/builder.py
xblock/bytecode.py
xblock/cli.py
xblock/compiler.py
xblock/crypto.py
xblock/kv_adapter.py
xblock/packager.py
xblock/runtime.py
xblock/security.py
xblock/utils.py
xblock/backends/__init__.py
xblock/backends/kivy.py
xblock/backends/native.py
xblock/backends/qt.py
xblock/backends/tkinter.py
xblock/backends/web.py
xblock_framework-0.1.0.dist-info/licenses/LICENSE
xblock_framework-0.1.0.dist-info/METADATA
xblock_framework-0.1.0.dist-info/WHEEL
xblock_framework-0.1.0.dist-info/entry_points.txt
xblock_framework-0.1.0.dist-info/top_level.txt
xblock_framework-0.1.0.dist-info/RECORD
